i18nfield/__init__.py
i18nfield/admin.py
i18nfield/fields.py
i18nfield/forms.py
i18nfield/rest_framework.py
i18nfield/strings.py
i18nfield/utils.py
django_i18nfield-1.10.1.dist-info/AUTHORS
django_i18nfield-1.10.1.dist-info/LICENSE
django_i18nfield-1.10.1.dist-info/METADATA
django_i18nfield-1.10.1.dist-info/WHEEL
django_i18nfield-1.10.1.dist-info/top_level.txt
django_i18nfield-1.10.1.dist-info/RECORD
