Metadata-Version: 2.1
Name: django-i18nfield
Version: 1.10.1
Summary: Store internationalized strings in Django models
Home-page: https://github.com/raphaelm/django-i18nfield
Author: Raphael Michel
Author-email: mail@raphaelmichel.de
License: Apache License 2.0
Keywords: i18n strings database models
Classifier: Intended Audience :: Developers
Classifier: Intended Audience :: Other Audience
Classifier: License :: OSI Approved :: Apache Software License
Classifier: Programming Language :: Python :: 3.4
Classifier: Programming Language :: Python :: 3.5
Classifier: Programming Language :: Python :: 3.6
Classifier: Framework :: Django :: 1.10
License-File: LICENSE
License-File: AUTHORS
